{"elapsed":"0.93","endpoint-url":"https://open.barnet.gov.uk/download/2nq32/fzw/Open%20Data%20Planning%202011-2012%20-%20NG.csv","entry-date":"2023-01-09T00:24:22.331387","request-headers":{"Accept":"*/*","Accept-Encoding":"gzip, deflate","Connection":"keep-alive","User-Agent":"DLUHC Digital Land"},"resource":"28afc46b0fbcb31c48ab63354ff94424b38aeb9918d8b58a696649bbe6df7122","response-headers":{"Access-Control-Allow-Origin":"*","CF-Cache-Status":"MISS","CF-RAY":"786907ca7ac35824-IAD","Cache-Control":"max-age=14400","Connection":"keep-alive","Content-Disposition":"attachment","Content-Encoding":"gzip","Content-Type":"text/csv; charset=utf-8","Date":"Mon, 09 Jan 2023 00:24:31 GMT","Etag":"\"6be69bd30317cd8e32a5220f6b74933d\"","Last-Modified":"Sat Apr 10 2021 01:08:37 GMT+0000 (Coordinated Universal Time)","NEL":"{\"success_fraction\":0,\"report_to\":\"cf-nel\",\"max_age\":604800}","Report-To":"{\"endpoints\":[{\"url\":\"https:\\/\\/a.nel.cloudflare.com\\/report\\/v3?s=DNdvEHTJesku%2BPy5zCGfQZv2eaKZ%2BlXo7jI9wVc2VlGAisxZTB3tmO8rfyK%2BAEl4oRlHaZRveuC9NQtLSw2cOAqExGHYOkpOuMFvLC%2BJ1lVUb62GcnQXulsbIzogKVU9GRk%2FMw%3D%3D\"}],\"group\":\"cf-nel\",\"max_age\":604800}","Server":"cloudflare","Transfer-Encoding":"chunked","Vary":"Accept-Encoding","Via":"1.1 vegur, 1.1 vegur"},"ssl-verify":true,"status":"200"}