{"elapsed":"9.839","endpoint-url":"https://geoserver.nottinghamcity.gov.uk/opendata/csv/attribute/ncc_PlanningApplications.csv","entry-date":"2023-01-20T00:26:40.014768","request-headers":{"Accept":"*/*","Accept-Encoding":"gzip, deflate","Connection":"keep-alive","User-Agent":"DLUHC Digital Land"},"resource":"12acc15b4157469122071bcc16f3fe11c16deab3a82e48bfb8ec7f4e64842afe","response-headers":{"Accept-Ranges":"bytes","Cache-Control":"max-age=86400, must-revalidate","Content-Encoding":"gzip","Content-Type":"application/octet-stream","Date":"Fri, 20 Jan 2023 00:26:28 GMT","ETag":"\"93775be8a42bd91:0\"","Last-Modified":"Thu, 19 Jan 2023 01:25:25 GMT","Referrer-Policy":"no-referrer-when-downgrade","Server":"nottinghamcity.gov.uk","Transfer-Encoding":"chunked","Vary":"Accept-Encoding","X-Content-Type-Options":"nosniff","X-XSS-Protection":"1;mode=block","x-frame-options":"SAMEORIGIN"},"ssl-verify":true,"status":"200"}