{"bytes":3476812,"elapsed":"1.008","endpoint-url":"https://open.barnet.gov.uk/download/2nq32/xl9/Open%20Data%20Planning%202020.csv","entry-date":"2022-03-31T00:22:18.275078","request-headers":{"Accept":"*/*","Accept-Encoding":"gzip, deflate","Connection":"keep-alive","User-Agent":"DLUHC Digital Land"},"resource":"aba03f618ef1f7c3450ec5d6e15deda75e8e2d45155b1c4dadf709eebd3e9dca","response-headers":{"CF-Cache-Status":"MISS","CF-RAY":"6f44ee22e91d8296-IAD","Cache-Control":"max-age=14400","Connection":"keep-alive","Content-Disposition":"attachment","Content-Encoding":"gzip","Content-Type":"text/csv; charset=utf-8","Date":"Thu, 31 Mar 2022 00:22:22 GMT","Etag":"\"fb5e41c6a3df88613799abdf639c9974\"","Expect-CT":"max-age=604800, report-uri=\"https://report-uri.cloudflare.com/cdn-cgi/beacon/expect-ct\"","Last-Modified":"Mon Feb 01 2021 16:21:35 GMT+0000 (Coordinated Universal Time)","NEL":"{\"success_fraction\":0,\"report_to\":\"cf-nel\",\"max_age\":604800}","Report-To":"{\"endpoints\":[{\"url\":\"https:\\/\\/a.nel.cloudflare.com\\/report\\/v3?s=hmuKX4ZrVKzlGv%2Fvx7aVVtKZI9lmRnDy%2B46sz%2FEZNi8fz0Lxoytyf1KVRu17Yp1tLSAC%2BZ6n202uB1f5aTvrtmK2WhJJisMWwk%2F9YL%2BVMlv8sNOfyMMvC1ZRj%2FZDPjWgvfm%2BWQ%3D%3D\"}],\"group\":\"cf-nel\",\"max_age\":604800}","Server":"cloudflare","Transfer-Encoding":"chunked","Vary":"Accept-Encoding","Via":"1.1 vegur, 1.1 vegur"},"ssl-verify":true,"status":"200"}