{"elapsed":"1.139","endpoint-url":"https://open.barnet.gov.uk/download/2nq32/9wj/Open%20Data%20Planning%202018-19%20-%20NG.csv","entry-date":"2022-08-13T00:25:53.050406","request-headers":{"Accept":"*/*","Accept-Encoding":"gzip, deflate","Connection":"keep-alive","User-Agent":"DLUHC Digital Land"},"resource":"c081b99d91eb2fa48a633b99c8a752a77b5d55a9b98ffa52f717054972856b50","response-headers":{"Access-Control-Allow-Origin":"*","CF-Cache-Status":"MISS","CF-RAY":"739d517cc9586458-SJC","Cache-Control":"max-age=14400","Connection":"keep-alive","Content-Disposition":"attachment","Content-Encoding":"gzip","Content-Type":"text/csv; charset=utf-8","Date":"Sat, 13 Aug 2022 00:26:16 GMT","Etag":"\"6773ac276c402765ebcc52086deea47d\"","Expect-CT":"max-age=604800, report-uri=\"https://report-uri.cloudflare.com/cdn-cgi/beacon/expect-ct\"","Last-Modified":"Sat Apr 10 2021 01:08:36 GMT+0000 (Coordinated Universal Time)","NEL":"{\"success_fraction\":0,\"report_to\":\"cf-nel\",\"max_age\":604800}","Report-To":"{\"endpoints\":[{\"url\":\"https:\\/\\/a.nel.cloudflare.com\\/report\\/v3?s=Hh2zS1Znbespe%2BmZOlde1YQtyS94qY34W9bRfulHnd9qd%2FvGj24wFuqyv7Rbdr6Ex8KWZfc9UwVg8izdVuC0r%2FH0Yu%2BCgszGnPl2yLp%2FVtXxkS1xuAo1Un%2BW6YzGZVb%2FDT8WYw%3D%3D\"}],\"group\":\"cf-nel\",\"max_age\":604800}","Server":"cloudflare","Transfer-Encoding":"chunked","Vary":"Accept-Encoding","Via":"1.1 vegur, 1.1 vegur"},"ssl-verify":true,"status":"200"}