{"elapsed":"16.414","endpoint-url":"https://geoserver.nottinghamcity.gov.uk/opendata/csv/attribute/ncc_PlanningApplications.csv","entry-date":"2022-10-07T00:40:21.429162","request-headers":{"Accept":"*/*","Accept-Encoding":"gzip, deflate","Connection":"keep-alive","User-Agent":"DLUHC Digital Land"},"resource":"b55668e264d44a1f251f41ce077e7a8a5ad25a0db866a835d00ce25fb40d7deb","response-headers":{"Accept-Ranges":"bytes","Content-Encoding":"gzip","Content-Type":"application/octet-stream","Date":"Fri, 07 Oct 2022 00:40:56 GMT","ETag":"\"c3883718e3d9d81:0\"","Last-Modified":"Fri, 07 Oct 2022 00:23:59 GMT","Referrer-Policy":"no-referrer-when-downgrade","Server":"nottinghamcity.gov.uk","Transfer-Encoding":"chunked","Vary":"Accept-Encoding","X-Content-Type-Options":"nosniff","X-XSS-Protection":"1;mode=block","x-frame-options":"SAMEORIGIN"},"ssl-verify":true,"status":"200"}