{"elapsed":"15.989","endpoint-url":"https://geoserver.nottinghamcity.gov.uk/opendata/csv/attribute/ncc_PlanningApplications.csv","entry-date":"2022-10-04T00:38:17.379879","request-headers":{"Accept":"*/*","Accept-Encoding":"gzip, deflate","Connection":"keep-alive","User-Agent":"DLUHC Digital Land"},"resource":"459fd24278417dd283d5d1a519e484d4a13eea8324fc4a053cb9c48de7bd918b","response-headers":{"Accept-Ranges":"bytes","Content-Encoding":"gzip","Content-Type":"application/octet-stream","Date":"Tue, 04 Oct 2022 00:38:42 GMT","ETag":"\"b4ed56af87d7d81:0\"","Last-Modified":"Tue, 04 Oct 2022 00:24:36 GMT","Referrer-Policy":"no-referrer-when-downgrade","Server":"nottinghamcity.gov.uk","Transfer-Encoding":"chunked","Vary":"Accept-Encoding","X-Content-Type-Options":"nosniff","X-XSS-Protection":"1;mode=block","x-frame-options":"SAMEORIGIN"},"ssl-verify":true,"status":"200"}