{"elapsed":"1.106","endpoint-url":"https://open.barnet.gov.uk/download/2nq32/9b3/Open%20Data%20Planning%202014-2015%20-%20NG.csv","entry-date":"2022-05-17T00:23:54.743028","request-headers":{"Accept":"*/*","Accept-Encoding":"gzip, deflate","Connection":"keep-alive","User-Agent":"DLUHC Digital Land"},"resource":"b97ba8470db74fd6772373af6208fd8ab40fb9ae1c820d5a7332c0545f8276ca","response-headers":{"CF-Cache-Status":"MISS","CF-RAY":"70c83552db745b3a-IAD","Cache-Control":"max-age=14400","Connection":"keep-alive","Content-Disposition":"attachment","Content-Encoding":"gzip","Content-Type":"text/csv; charset=utf-8","Date":"Tue, 17 May 2022 00:24:07 GMT","Etag":"\"c33361bc059b3d78ed89369c27dd6ee1\"","Expect-CT":"max-age=604800, report-uri=\"https://report-uri.cloudflare.com/cdn-cgi/beacon/expect-ct\"","Last-Modified":"Sat Apr 10 2021 01:08:37 GMT+0000 (Coordinated Universal Time)","NEL":"{\"success_fraction\":0,\"report_to\":\"cf-nel\",\"max_age\":604800}","Report-To":"{\"endpoints\":[{\"url\":\"https:\\/\\/a.nel.cloudflare.com\\/report\\/v3?s=Id0DhJx8r4L4y4S4MXhE%2BdLFpx3V2CkyZ357LMIMo0agLZh6yFOyP4pt9g8coEygFh6RzmePj3Fv1sEd81FWjrMk7kND9KpgQWLHuIUC8f6oVC5sBIFi8T%2BfLuAiDrWLQOv8Rg%3D%3D\"}],\"group\":\"cf-nel\",\"max_age\":604800}","Server":"cloudflare","Transfer-Encoding":"chunked","Vary":"Accept-Encoding","Via":"1.1 vegur, 1.1 vegur"},"ssl-verify":true,"status":"200"}